ccmm_invenio/__init__.py
ccmm_invenio/conversion/__init__.py
ccmm_invenio/conversion/base.py
ccmm_invenio/conversion/ccmm_copy.py
ccmm_invenio/conversion/ccmm_csv.py
ccmm_invenio/conversion/ccmm_filtered.py
ccmm_invenio/conversion/ccmm_sparql.py
ccmm_invenio/conversion/convert_vocabularies.py
ccmm_invenio/fixtures/__init__.py
ccmm_invenio/fixtures/catalogue.yaml
ccmm_invenio/fixtures/ccmm_access_rights.yaml
ccmm_invenio/fixtures/ccmm_agent_roles.yaml
ccmm_invenio/fixtures/ccmm_alternate_title_types.yaml
ccmm_invenio/fixtures/ccmm_checksum_algorithms.yaml
ccmm_invenio/fixtures/ccmm_contributor_types.yaml
ccmm_invenio/fixtures/ccmm_file_types.yaml
ccmm_invenio/fixtures/ccmm_identifier_schemes.yaml
ccmm_invenio/fixtures/ccmm_languages.yaml
ccmm_invenio/fixtures/ccmm_licenses.yaml
ccmm_invenio/fixtures/ccmm_location_relation_types.yaml
ccmm_invenio/fixtures/ccmm_relation_types.yaml
ccmm_invenio/fixtures/ccmm_resource_types.yaml
ccmm_invenio/fixtures/ccmm_subject_categories.yaml
ccmm_invenio/fixtures/ccmm_subject_schemes.yaml
ccmm_invenio/fixtures/ccmm_time_reference_types.yaml
ccmm_invenio-0.2.3.dist-info/licenses/LICENSE
ccmm_invenio-0.2.3.dist-info/METADATA
ccmm_invenio-0.2.3.dist-info/WHEEL
ccmm_invenio-0.2.3.dist-info/entry_points.txt
ccmm_invenio-0.2.3.dist-info/top_level.txt
ccmm_invenio-0.2.3.dist-info/RECORD
