Metadata-Version: 2.4
Name: ccmm-invenio
Version: 0.2.3
Summary: CCMM (Czech Core Metadata Model) components for NRP Invenio
License-File: LICENSE
Provides-Extra: compile-vocabularies
Requires-Dist: rdflib; extra == "compile-vocabularies"
Requires-Dist: click; extra == "compile-vocabularies"
Requires-Dist: tenacity; extra == "compile-vocabularies"
Requires-Dist: pyyaml; extra == "compile-vocabularies"
Requires-Dist: tqdm; extra == "compile-vocabularies"
Dynamic: license-file
